pyvscode/__init__.py
pyvscode/extension.py
pyvscode/extension.pyi
pyvscode/pyvscode.py
pyvscode/pyvscode.pyi
pyvscode/runner.py
pyvscode/runner.pyi
pyvscode-2.2.1.dist-info/METADATA
pyvscode-2.2.1.dist-info/WHEEL
pyvscode-2.2.1.dist-info/licenses/LICENSE
pyvscode-2.2.1.dist-info/RECORD
