Metadata-Version: 2.1
Name: pyvscode
Version: 2.2.1
Summary: Package for interacting with IDE called Visual Studio Code.
Project-URL: Repository, https://github.com/KrazyManJ/pyvscode
Project-URL: Bug Tracker, https://github.com/KrazyManJ/pyvscode/issues
Author: KrazyManJ
License-File: LICENSE
Classifier: License :: OSI Approved :: MIT License
Classifier: Operating System :: OS Independent
Classifier: Programming Language :: Python :: 3
Classifier: Typing :: Typed
Requires-Python: >=3.7
Requires-Dist: dataclasses
Requires-Dist: subprocess
